sphinx_tags/__init__.py
sphinx_tags_fork-0.2.0.dist-info/LICENSE
sphinx_tags_fork-0.2.0.dist-info/WHEEL
sphinx_tags_fork-0.2.0.dist-info/METADATA
sphinx_tags_fork-0.2.0.dist-info/RECORD
