Metadata-Version: 2.1
Name: sphinx-tags-fork
Version: 0.2.0
Summary: Sphinx extension to create tags for documentation pages.
Keywords: documentation,sphinx
Author-email: alex <alexurban12@gmail.com>
Classifier: License :: OSI Approved :: MIT License
Requires-Dist: sphinx>4
Requires-Dist: pre-commit
Requires-Dist: pydata-sphinx-theme ; extra == "sphinx"
Requires-Dist: sphinx-design ; extra == "sphinx"
Requires-Dist: myst-parser ; extra == "sphinx"
Project-URL: Home, https://github.com/melissawm/sphinx-tags
Provides-Extra: sphinx
